fbtcore/__init__.py
fbtcore/concurrent.py
fbtcore/core.py
fbtcore-2.0.1.dist-info/LICENSE
fbtcore-2.0.1.dist-info/METADATA
fbtcore-2.0.1.dist-info/WHEEL
fbtcore-2.0.1.dist-info/top_level.txt
fbtcore-2.0.1.dist-info/RECORD
