Metadata-Version: 2.2
Name: fbtcore
Version: 2.0.1
Summary: FBtree 2.0 - 高性能线程安全的树结构库
Home-page: https://github.com/Karesis/FBtree2.0
Author: Karesis
Author-email: yangyifeng23@mails.ucas.ac.cn
Classifier: Programming Language :: Python :: 3
Classifier: License :: OSI Approved :: GNU Lesser General Public License v3 (LGPLv3)
Classifier: Operating System :: OS Independent
Requires-Python: >=3.7
License-File: LICENSE
Requires-Dist: numpy
Requires-Dist: matplotlib
Dynamic: author
Dynamic: author-email
Dynamic: classifier
Dynamic: description
Dynamic: description-content-type
Dynamic: home-page
Dynamic: requires-dist
Dynamic: requires-python
Dynamic: summary
